degiro_connector/__init__.py
degiro_connector/core/__init__.py
degiro_connector/core/exceptions.py
degiro_connector/core/abstracts/__init__.py
degiro_connector/core/abstracts/abstract_action.py
degiro_connector/core/constants/__init__.py
degiro_connector/core/constants/headers.py
degiro_connector/core/constants/urls.py
degiro_connector/core/helpers/__init__.py
degiro_connector/core/helpers/lazy_loader.py
degiro_connector/core/models/__init__.py
degiro_connector/core/models/model_connection.py
degiro_connector/core/models/model_session.py
degiro_connector/quotecast/__init__.py
degiro_connector/quotecast/api.py
degiro_connector/quotecast/models/__init__.py
degiro_connector/quotecast/models/chart.py
degiro_connector/quotecast/models/message.py
degiro_connector/quotecast/models/metric.py
degiro_connector/quotecast/models/ticker.py
degiro_connector/quotecast/tools/__init__.py
degiro_connector/quotecast/tools/chart_fetcher.py
degiro_connector/quotecast/tools/ticker_fetcher.py
degiro_connector/quotecast/tools/ticker_to_df.py
degiro_connector/quotecast/tools/ticker_to_metric_list.py
degiro_connector/trading/__init__.py
degiro_connector/trading/api.py
degiro_connector/trading/actions/__init__.py
degiro_connector/trading/actions/action_check_order.py
degiro_connector/trading/actions/action_confirm_order.py
degiro_connector/trading/actions/action_connect.py
degiro_connector/trading/actions/action_create_favorite.py
degiro_connector/trading/actions/action_create_note.py
degiro_connector/trading/actions/action_delete_favorite.py
degiro_connector/trading/actions/action_delete_favorite_product.py
degiro_connector/trading/actions/action_delete_note.py
degiro_connector/trading/actions/action_delete_order.py
degiro_connector/trading/actions/action_edit_note.py
degiro_connector/trading/actions/action_get_account_info.py
degiro_connector/trading/actions/action_get_account_overview.py
degiro_connector/trading/actions/action_get_account_report.py
degiro_connector-3.0.34.dist-info/licenses/LICENSE
degiro_connector-3.0.34.dist-info/METADATA
degiro_connector-3.0.34.dist-info/WHEEL
degiro_connector-3.0.34.dist-info/top_level.txt
degiro_connector-3.0.34.dist-info/RECORD
