Metadata-Version: 2.4
Name: degiro-connector
Version: 3.0.34
Summary: This is yet another library to access Degiro's API.
Author-email: Chavithra PARANA <chavithra@gmail.com>
License-Expression: BSD-3-Clause
Project-URL: repository, https://github.com/chavithra/degiro-connector
Classifier: Programming Language :: Python :: 3
Classifier: Operating System :: OS Independent
Requires-Python: >=3.10
License-File: LICENSE
Requires-Dist: isodate>=0.6.1
Requires-Dist: orjson>=3.11.3
Requires-Dist: pydantic>=2.11.7
Requires-Dist: pyotp>=2.9.0
Requires-Dist: requests>=2.32.5
Requires-Dist: wrapt==1.14.1
Provides-Extra: dev
Requires-Dist: black>=25.1.0; extra == "dev"
Requires-Dist: flake8>=7.3.0; extra == "dev"
Requires-Dist: mypy>=1.17.1; extra == "dev"
Requires-Dist: pytest>=8.4.1; extra == "dev"
Requires-Dist: pytest-mock>=3.14.1; extra == "dev"
Requires-Dist: types-requests>=2.32.4.20250809; extra == "dev"
Provides-Extra: qrcode
Requires-Dist: opencv-python>=4.12.0.88; extra == "qrcode"
Provides-Extra: quotecast
Requires-Dist: polars>=1.33.0; extra == "quotecast"
Dynamic: license-file
